Workbook

Sheet Formato Creditos
E1: Indice | F1: Cuota | G1: Fecha Pago | H1: Saldo proyectado | I1: Saldo real | J1: Abono a capital | K1: Interes Proyectado | L1: Interes Real | M1: Abono total Proyectado | N1: Abono total real | O1: Abono Pagado
E2: 1 | F2: ='Formato Creditos'!$E2 -> 1 | G2: =DATE(YEAR($B$8),MONTH($B$8)+'Formato Creditos'!$E2,DAY($B$8)) -> 45914 | H2: =+B4 -> 1200000 | I2: =+B4 -> 1200000 | J2: =IF('Formato Creditos'!$H2<=0,"",IF(F2="","",$B$7)) -> 100000 | K2: =ROUNDUP(H2*$B$6,-3) -> 24000 | L2: =ROUNDUP(I2*$B$6,-3) -> 24000 | M2: =IFERROR(IF('Formato Creditos'!$H2<=0,"",IF(('Formato Creditos'!$H2+'Formato Creditos'!$K2)>('Formato Creditos'!$J2+'Formato Creditos'!$K2),ROUNDUP(('Formato Creditos'!$J2+'Formato Creditos'!$K2),-3),ROUNDUP('Formato Creditos'!$H2+'Formato Creditos'!$K2,-3))),"") -> 124000 | N2: =IFERROR(IF('Formato Creditos'!$I2<=0,"",IF(('Formato Creditos'!$I2+'Formato Creditos'!$K2)>('Formato Creditos'!$J2+'Formato Creditos'!$K2),ROUNDUP(('Formato Creditos'!$J2+'Formato Creditos'!$K2),-3),ROUNDUP('Formato Creditos'!$I2+'Formato Creditos'!$K2,-3))),"") -> 124000 | O2: =M2 -> 124000
A3: Acreedor del credito | B3: Yohan Moreno | E3: 2 | F3: =IFERROR(IF(ROUND(H2,-3)<=0,"",'Formato Creditos'!$E3),"") -> 2 | G3: =IFERROR(IF('Formato Creditos'!$F3="","",DATE(YEAR($B$8),MONTH($B$8)+'Formato Creditos'!$E3,DAY($B$8))),"") -> 45944 | H3: =IFERROR(IF('Formato Creditos'!$F3="","",H2-(M2-K2)),"") -> 1100000 | I3: =IFERROR(IF((I2-(O2-K2))<=0,0,IF('Formato Creditos'!$F3="","",I2-(O2-K2))),"") -> 1100000 | J3: =IF('Formato Creditos'!$H3<=0,"",IF(F3="","",$B$7)) -> 100000 | K3: =ROUNDUP(H3*$B$6,-3) -> 22000 | L3: =ROUNDUP(I3*$B$6,-3) -> 22000 | M3: =IFERROR(IF('Formato Creditos'!$H3<=0,"",IF(('Formato Creditos'!$H3+'Formato Creditos'!$K3)>('Formato Creditos'!$J3+'Formato Creditos'!$K3),ROUNDUP(('Formato Creditos'!$J3+'Formato Creditos'!$K3),-3),ROUNDUP('Formato Creditos'!$H3+'Formato Creditos'!$K3,-3))),"") -> 122000 | N3: =IFERROR(IF('Formato Creditos'!$I3<=0,"",IF(('Formato Creditos'!$I3+'Formato Creditos'!$K3)>('Formato Creditos'!$J3+'Formato Creditos'!$K3),ROUNDUP(('Formato Creditos'!$J3+'Formato Creditos'!$K3),-3),ROUNDUP('Formato Creditos'!$I3+'Formato Creditos'!$K3,-3))),"") -> 122000 | O3: =M3 -> 122000
A4: Monto | B4: 1200000 | E4: 3 | F4: =IFERROR(IF(ROUND(H3,-3)<=0,"",'Formato Creditos'!$E4),"") -> 3 | G4: =IFERROR(IF('Formato Creditos'!$F4="","",DATE(YEAR($B$8),MONTH($B$8)+'Formato Creditos'!$E4,DAY($B$8))),"") -> 45975 | H4: =IFERROR(IF('Formato Creditos'!$F4="","",H3-(M3-K3)),"") -> 1000000 | I4: =IFERROR(IF((I3-(O3-K3))<=0,0,IF('Formato Creditos'!$F4="","",I3-(O3-K3))),"") -> 1000000 | J4: =IF('Formato Creditos'!$H4<=0,"",IF(F4="","",$B$7)) -> 100000 | K4: =ROUNDUP(H4*$B$6,-3) -> 20000 | L4: =ROUNDUP(I4*$B$6,-3) -> 20000 | M4: =IFERROR(IF('Formato Creditos'!$H4<=0,"",IF(('Formato Creditos'!$H4+'Formato Creditos'!$K4)>('Formato Creditos'!$J4+'Formato Creditos'!$K4),ROUNDUP(('Formato Creditos'!$J4+'Formato Creditos'!$K4),-3),ROUNDUP('Formato Creditos'!$H4+'Formato Creditos'!$K4,-3))),"") -> 120000 | N4: =IFERROR(IF('Formato Creditos'!$I4<=0,"",IF(('Formato Creditos'!$I4+'Formato Creditos'!$K4)>('Formato Creditos'!$J4+'Formato Creditos'!$K4),ROUNDUP(('Formato Creditos'!$J4+'Formato Creditos'!$K4),-3),ROUNDUP('Formato Creditos'!$I4+'Formato Creditos'!$K4,-3))),"") -> 120000 | O4: =IF(F4="","",M4) -> 120000
A5: Número de cuotas | B5: 12 | E5: 4 | F5: =IFERROR(IF(ROUND(H4,-3)<=0,"",'Formato Creditos'!$E5),"") -> 4 | G5: =IFERROR(IF('Formato Creditos'!$F5="","",DATE(YEAR($B$8),MONTH($B$8)+'Formato Creditos'!$E5,DAY($B$8))),"") -> 46005 | H5: =IFERROR(IF('Formato Creditos'!$F5="","",H4-(M4-K4)),"") -> 900000 | I5: =IFERROR(IF((I4-(O4-K4))<=0,0,IF('Formato Creditos'!$F5="","",I4-(O4-K4))),"") -> 900000 | J5: =IF('Formato Creditos'!$H5<=0,"",IF(F5="","",$B$7)) -> 100000 | K5: =ROUNDUP(H5*$B$6,-3) -> 18000 | L5: =ROUNDUP(I5*$B$6,-3) -> 18000 | M5: =IFERROR(IF('Formato Creditos'!$H5<=0,"",IF(('Formato Creditos'!$H5+'Formato Creditos'!$K5)>('Formato Creditos'!$J5+'Formato Creditos'!$K5),ROUNDUP(('Formato Creditos'!$J5+'Formato Creditos'!$K5),-3),ROUNDUP('Formato Creditos'!$H5+'Formato Creditos'!$K5,-3))),"") -> 118000 | N5: =IFERROR(IF('Formato Creditos'!$I5<=0,"",IF(('Formato Creditos'!$I5+'Formato Creditos'!$K5)>('Formato Creditos'!$J5+'Formato Creditos'!$K5),ROUNDUP(('Formato Creditos'!$J5+'Formato Creditos'!$K5),-3),ROUNDUP('Formato Creditos'!$I5+'Formato Creditos'!$K5,-3))),"") -> 118000 | O5: =IF(F5="","",M5) -> 118000
A6: Tasa de interes | B6: 0.02 | E6: 5 | F6: =IFERROR(IF(ROUND(H5,-3)<=0,"",'Formato Creditos'!$E6),"") -> 5 | G6: =IFERROR(IF('Formato Creditos'!$F6="","",DATE(YEAR($B$8),MONTH($B$8)+'Formato Creditos'!$E6,DAY($B$8))),"") -> 46036 | H6: =IFERROR(IF('Formato Creditos'!$F6="","",H5-(M5-K5)),"") -> 800000 | I6: =IFERROR(IF((I5-(O5-K5))<=0,0,IF('Formato Creditos'!$F6="","",I5-(O5-K5))),"") -> 800000 | J6: =IF('Formato Creditos'!$H6<=0,"",IF(F6="","",$B$7)) -> 100000 | K6: =ROUNDUP(H6*$B$6,-3) -> 16000 | L6: =ROUNDUP(I6*$B$6,-3) -> 16000 | M6: =IFERROR(IF('Formato Creditos'!$H6<=0,"",IF(('Formato Creditos'!$H6+'Formato Creditos'!$K6)>('Formato Creditos'!$J6+'Formato Creditos'!$K6),ROUNDUP(('Formato Creditos'!$J6+'Formato Creditos'!$K6),-3),ROUNDUP('Formato Creditos'!$H6+'Formato Creditos'!$K6,-3))),"") -> 116000 | N6: =IFERROR(IF('Formato Creditos'!$I6<=0,"",IF(('Formato Creditos'!$I6+'Formato Creditos'!$K6)>('Formato Creditos'!$J6+'Formato Creditos'!$K6),ROUNDUP(('Formato Creditos'!$J6+'Formato Creditos'!$K6),-3),ROUNDUP('Formato Creditos'!$I6+'Formato Creditos'!$K6,-3))),"") -> 116000 | O6: =IF(F6="","",M6) -> 116000
A7: Valor cuota fija | B7: =ROUNDUP(B4/B5,-3) -> 100000 | E7: 6 | F7: =IFERROR(IF(ROUND(H6,-3)<=0,"",'Formato Creditos'!$E7),"") -> 6 | G7: =IFERROR(IF('Formato Creditos'!$F7="","",DATE(YEAR($B$8),MONTH($B$8)+'Formato Creditos'!$E7,DAY($B$8))),"") -> 46067 | H7: =IFERROR(IF('Formato Creditos'!$F7="","",H6-(M6-K6)),"") -> 700000 | I7: =IFERROR(IF((I6-(O6-K6))<=0,0,IF('Formato Creditos'!$F7="","",I6-(O6-K6))),"") -> 700000 | J7: =IF('Formato Creditos'!$H7<=0,"",IF(F7="","",$B$7)) -> 100000 | K7: =ROUNDUP(H7*$B$6,-3) -> 14000 | L7: =ROUNDUP(I7*$B$6,-3) -> 14000 | M7: =IFERROR(IF('Formato Creditos'!$H7<=0,"",IF(('Formato Creditos'!$H7+'Formato Creditos'!$K7)>('Formato Creditos'!$J7+'Formato Creditos'!$K7),ROUNDUP(('Formato Creditos'!$J7+'Formato Creditos'!$K7),-3),ROUNDUP('Formato Creditos'!$H7+'Formato Creditos'!$K7,-3))),"") -> 114000 | N7: =IFERROR(IF('Formato Creditos'!$I7<=0,"",IF(('Formato Creditos'!$I7+'Formato Creditos'!$K7)>('Formato Creditos'!$J7+'Formato Creditos'!$K7),ROUNDUP(('Formato Creditos'!$J7+'Formato Creditos'!$K7),-3),ROUNDUP('Formato Creditos'!$I7+'Formato Creditos'!$K7,-3))),"") -> 114000 | O7: =IF(F7="","",M7) -> 114000
A8: Fecha de inicio | B8: 45883 | E8: 7 | F8: =IFERROR(IF(ROUND(H7,-3)<=0,"",'Formato Creditos'!$E8),"") -> 7 | G8: =IFERROR(IF('Formato Creditos'!$F8="","",DATE(YEAR($B$8),MONTH($B$8)+'Formato Creditos'!$E8,DAY($B$8))),"") -> 46095 | H8: =IFERROR(IF('Formato Creditos'!$F8="","",H7-(M7-K7)),"") -> 600000 | I8: =IFERROR(IF((I7-(O7-K7))<=0,0,IF('Formato Creditos'!$F8="","",I7-(O7-K7))),"") -> 600000 | J8: =IF('Formato Creditos'!$H8<=0,"",IF(F8="","",$B$7)) -> 100000 | K8: =ROUNDUP(H8*$B$6,-3) -> 12000 | L8: =ROUNDUP(I8*$B$6,-3) -> 12000 | M8: =IFERROR(IF('Formato Creditos'!$H8<=0,"",IF(('Formato Creditos'!$H8+'Formato Creditos'!$K8)>('Formato Creditos'!$J8+'Formato Creditos'!$K8),ROUNDUP(('Formato Creditos'!$J8+'Formato Creditos'!$K8),-3),ROUNDUP('Formato Creditos'!$H8+'Formato Creditos'!$K8,-3))),"") -> 112000 | N8: =IFERROR(IF('Formato Creditos'!$I8<=0,"",IF(('Formato Creditos'!$I8+'Formato Creditos'!$K8)>('Formato Creditos'!$J8+'Formato Creditos'!$K8),ROUNDUP(('Formato Creditos'!$J8+'Formato Creditos'!$K8),-3),ROUNDUP('Formato Creditos'!$I8+'Formato Creditos'!$K8,-3))),"") -> 112000 | O8: =IF(F8="","",M8) -> 112000
A9: Fecha Final | B9: =+B8+DATE(0,B5,-1) -> 46217 | E9: 8 | F9: =IFERROR(IF(ROUND(H8,-3)<=0,"",'Formato Creditos'!$E9),"") -> 8 | G9: =IFERROR(IF('Formato Creditos'!$F9="","",DATE(YEAR($B$8),MONTH($B$8)+'Formato Creditos'!$E9,DAY($B$8))),"") -> 46126 | H9: =IFERROR(IF('Formato Creditos'!$F9="","",H8-(M8-K8)),"") -> 500000 | I9: =IFERROR(IF((I8-(O8-K8))<=0,0,IF('Formato Creditos'!$F9="","",I8-(O8-K8))),"") -> 500000 | J9: =IF('Formato Creditos'!$H9<=0,"",IF(F9="","",$B$7)) -> 100000 | K9: =ROUNDUP(H9*$B$6,-3) -> 10000 | L9: =ROUNDUP(I9*$B$6,-3) -> 10000 | M9: =IFERROR(IF('Formato Creditos'!$H9<=0,"",IF(('Formato Creditos'!$H9+'Formato Creditos'!$K9)>('Formato Creditos'!$J9+'Formato Creditos'!$K9),ROUNDUP(('Formato Creditos'!$J9+'Formato Creditos'!$K9),-3),ROUNDUP('Formato Creditos'!$H9+'Formato Creditos'!$K9,-3))),"") -> 110000 | N9: =IFERROR(IF('Formato Creditos'!$I9<=0,"",IF(('Formato Creditos'!$I9+'Formato Creditos'!$K9)>('Formato Creditos'!$J9+'Formato Creditos'!$K9),ROUNDUP(('Formato Creditos'!$J9+'Formato Creditos'!$K9),-3),ROUNDUP('Formato Creditos'!$I9+'Formato Creditos'!$K9,-3))),"") -> 110000 | O9: =IF(F9="","",M9) -> 110000
A10: Total A Pagar | B10: ='Formato Creditos'!$O$16 -> 1356000 | E10: 9 | F10: =IFERROR(IF(ROUND(H9,-3)<=0,"",'Formato Creditos'!$E10),"") -> 9 | G10: =IFERROR(IF('Formato Creditos'!$F10="","",DATE(YEAR($B$8),MONTH($B$8)+'Formato Creditos'!$E10,DAY($B$8))),"") -> 46156 | H10: =IFERROR(IF('Formato Creditos'!$F10="","",H9-(M9-K9)),"") -> 400000 | I10: =IFERROR(IF((I9-(O9-K9))<=0,0,IF('Formato Creditos'!$F10="","",I9-(O9-K9))),"") -> 400000 | J10: =IF('Formato Creditos'!$H10<=0,"",IF(F10="","",$B$7)) -> 100000 | K10: =IF(F10="","",H10*$B$6) -> 8000 | L10: =IF(F10="","",I10*$B$6) -> 8000 | M10: =IFERROR(IF('Formato Creditos'!$H10<=0,"",IF(('Formato Creditos'!$H10+'Formato Creditos'!$K10)>('Formato Creditos'!$J10+'Formato Creditos'!$K10),ROUNDUP(('Formato Creditos'!$J10+'Formato Creditos'!$K10),-3),ROUNDUP('Formato Creditos'!$H10+'Formato Creditos'!$K10,-3))),"") -> 108000 | N10: =IFERROR(IF('Formato Creditos'!$I10<=0,"",IF(('Formato Creditos'!$I10+'Formato Creditos'!$K10)>('Formato Creditos'!$J10+'Formato Creditos'!$K10),ROUNDUP(('Formato Creditos'!$J10+'Formato Creditos'!$K10),-3),ROUNDUP('Formato Creditos'!$I10+'Formato Creditos'!$K10,-3))),"") -> 108000 | O10: =IF(F10="","",M10) -> 108000
A11: Total interes a pagar | B11: ='Formato Creditos'!$K$16 -> 156000 | E11: 10 | F11: =IFERROR(IF(ROUND(H10,-3)<=0,"",'Formato Creditos'!$E11),"") -> 10 | G11: =IFERROR(IF('Formato Creditos'!$F11="","",DATE(YEAR($B$8),MONTH($B$8)+'Formato Creditos'!$E11,DAY($B$8))),"") -> 46187 | H11: =IFERROR(IF('Formato Creditos'!$F11="","",H10-(M10-K10)),"") -> 300000 | I11: =IFERROR(IF((I10-(O10-K10))<=0,0,IF('Formato Creditos'!$F11="","",I10-(O10-K10))),"") -> 300000 | J11: =IF('Formato Creditos'!$H11<=0,"",IF(F11="","",$B$7)) -> 100000 | K11: =IF(F11="","",H11*$B$6) -> 6000 | L11: =IF(F11="","",I11*$B$6) -> 6000 | M11: =IFERROR(IF('Formato Creditos'!$H11<=0,"",IF(('Formato Creditos'!$H11+'Formato Creditos'!$K11)>('Formato Creditos'!$J11+'Formato Creditos'!$K11),ROUNDUP(('Formato Creditos'!$J11+'Formato Creditos'!$K11),-3),ROUNDUP('Formato Creditos'!$H11+'Formato Creditos'!$K11,-3))),"") -> 106000 | N11: =IFERROR(IF('Formato Creditos'!$I11<=0,"",IF(('Formato Creditos'!$I11+'Formato Creditos'!$K11)>('Formato Creditos'!$J11+'Formato Creditos'!$K11),ROUNDUP(('Formato Creditos'!$J11+'Formato Creditos'!$K11),-3),ROUNDUP('Formato Creditos'!$I11+'Formato Creditos'!$K11,-3))),"") -> 106000 | O11: =IF(F11="","",M11) -> 106000
E12: 11 | F12: =IFERROR(IF(ROUND(H11,-3)<=0,"",'Formato Creditos'!$E12),"") -> 11 | G12: =IFERROR(IF('Formato Creditos'!$F12="","",DATE(YEAR($B$8),MONTH($B$8)+'Formato Creditos'!$E12,DAY($B$8))),"") -> 46217 | H12: =IFERROR(IF('Formato Creditos'!$F12="","",H11-(M11-K11)),"") -> 200000 | I12: =IFERROR(IF((I11-(O11-K11))<=0,0,IF('Formato Creditos'!$F12="","",I11-(O11-K11))),"") -> 200000 | J12: =IF('Formato Creditos'!$H12<=0,"",IF(F12="","",$B$7)) -> 100000 | K12: =IF(F12="","",H12*$B$6) -> 4000 | L12: =IF(F12="","",I12*$B$6) -> 4000 | M12: =IFERROR(IF('Formato Creditos'!$H12<=0,"",IF(('Formato Creditos'!$H12+'Formato Creditos'!$K12)>('Formato Creditos'!$J12+'Formato Creditos'!$K12),ROUNDUP(('Formato Creditos'!$J12+'Formato Creditos'!$K12),-3),ROUNDUP('Formato Creditos'!$H12+'Formato Creditos'!$K12,-3))),"") -> 104000 | N12: =IFERROR(IF('Formato Creditos'!$I12<=0,"",IF(('Formato Creditos'!$I12+'Formato Creditos'!$K12)>('Formato Creditos'!$J12+'Formato Creditos'!$K12),ROUNDUP(('Formato Creditos'!$J12+'Formato Creditos'!$K12),-3),ROUNDUP('Formato Creditos'!$I12+'Formato Creditos'!$K12,-3))),"") -> 104000 | O12: =IF(F12="","",M12) -> 104000
E13: 30 | F13: =IFERROR(IF(ROUND(H12,-3)<=0,"",'Formato Creditos'!$E13),"") -> 30 | G13: =IFERROR(IF('Formato Creditos'!$F13="","",DATE(YEAR($B$8),MONTH($B$8)+'Formato Creditos'!$E13,DAY($B$8))),"") -> 46797 | H13: =IFERROR(IF('Formato Creditos'!$F13="","",H12-(M12-K12)),"") -> 100000 | I13: =IFERROR(IF((I12-(O12-K12))<=0,0,IF('Formato Creditos'!$F13="","",I12-(O12-K12))),"") -> 100000 | J13: =IF('Formato Creditos'!$H13<=0,"",IF(F13="","",$B$7)) -> 100000 | K13: =IF(F13="","",H13*$B$6) -> 2000 | L13: =IF(F13="","",I13*$B$6) -> 2000 | M13: =IFERROR(IF('Formato Creditos'!$H13<=0,"",IF(('Formato Creditos'!$H13+'Formato Creditos'!$K13)>('Formato Creditos'!$J13+'Formato Creditos'!$K13),ROUNDUP(('Formato Creditos'!$J13+'Formato Creditos'!$K13),-3),ROUNDUP('Formato Creditos'!$H13+'Formato Creditos'!$K13,-3))),"") -> 102000 | N13: =IFERROR(IF('Formato Creditos'!$I13<=0,"",IF(('Formato Creditos'!$I13+'Formato Creditos'!$K13)>('Formato Creditos'!$J13+'Formato Creditos'!$K13),ROUNDUP(('Formato Creditos'!$J13+'Formato Creditos'!$K13),-3),ROUNDUP('Formato Creditos'!$I13+'Formato Creditos'!$K13,-3))),"") -> 102000 | O13: =IF(F13="","",M13) -> 102000
E14: 31 | F14: =IFERROR(IF(ROUND(H13,-3)<=0,"",'Formato Creditos'!$E14),"") -> 31 | G14: =IFERROR(IF('Formato Creditos'!$F14="","",DATE(YEAR($B$8),MONTH($B$8)+'Formato Creditos'!$E14,DAY($B$8))),"") -> 46826 | H14: =IFERROR(IF('Formato Creditos'!$F14="","",H13-(M13-K13)),"") -> 0 | I14: =IFERROR(IF((I13-(O13-K13))<=0,0,IF('Formato Creditos'!$F14="","",I13-(O13-K13))),"") -> 0 | J14: =IF('Formato Creditos'!$H14<=0,"",IF(F14="","",$B$7)) | K14: =IF(F14="","",H14*$B$6) -> 0 | L14: =IF(F14="","",I14*$B$6) -> 0 | M14: =IFERROR(IF('Formato Creditos'!$H14<=0,"",IF(('Formato Creditos'!$H14+'Formato Creditos'!$K14)>('Formato Creditos'!$J14+'Formato Creditos'!$K14),ROUNDUP(('Formato Creditos'!$J14+'Formato Creditos'!$K14),-3),ROUNDUP('Formato Creditos'!$H14+'Formato Creditos'!$K14,-3))),"") | N14: =IFERROR(IF('Formato Creditos'!$I14<=0,"",IF(('Formato Creditos'!$I14+'Formato Creditos'!$K14)>('Formato Creditos'!$J14+'Formato Creditos'!$K14),ROUNDUP(('Formato Creditos'!$J14+'Formato Creditos'!$K14),-3),ROUNDUP('Formato Creditos'!$I14+'Formato Creditos'!$K14,-3))),"") | O14: =IF(F14="","",M14)
E15: 32 | F15: =IFERROR(IF(ROUND(H14,-3)<=0,"",'Formato Creditos'!$E15),"") | G15: =IFERROR(IF('Formato Creditos'!$F15="","",DATE(YEAR($B$8),MONTH($B$8)+'Formato Creditos'!$E15,DAY($B$8))),"") | H15: =IFERROR(IF('Formato Creditos'!$F15="","",H14-(M14-K14)),"") | I15: =IFERROR(IF((I14-(O14-K14))<=0,0,IF('Formato Creditos'!$F15="","",I14-(O14-K14))),"") -> 0 | J15: =IF('Formato Creditos'!$H15<=0,"",IF(F15="","",$B$7)) | K15: =IF(F15="","",H15*$B$6) | L15: =IF(F15="","",I15*$B$6) | M15: =IFERROR(IF('Formato Creditos'!$H15<=0,"",IF(('Formato Creditos'!$H15+'Formato Creditos'!$K15)>('Formato Creditos'!$J15+'Formato Creditos'!$K15),ROUNDUP(('Formato Creditos'!$J15+'Formato Creditos'!$K15),-3),ROUNDUP('Formato Creditos'!$H15+'Formato Creditos'!$K15,-3))),"") -> 0 | N15: =IFERROR(IF('Formato Creditos'!$I15<=0,"",IF(('Formato Creditos'!$I15+'Formato Creditos'!$K15)>('Formato Creditos'!$J15+'Formato Creditos'!$K15),ROUNDUP(('Formato Creditos'!$J15+'Formato Creditos'!$K15),-3),ROUNDUP('Formato Creditos'!$I15+'Formato Creditos'!$K15,-3))),"") | O15: =IF(F15="","",M15)
E16: Total | K16: =SUBTOTAL(109,'Formato Creditos'!$K$2:$K$15) -> 156000 | M16: =SUBTOTAL(109,'Formato Creditos'!$M$2:$M$15) -> 1356000 | O16: =SUBTOTAL(109,'Formato Creditos'!$O$2:$O$15) -> 1356000
F18: Crédito pagado
F19: =SUM(J2:J6) -> 500000
